magicrf/CONSTANT.py
magicrf/__init__.py
magicrf/_m100.cp39-win_amd64.pyd
magicrf/case1.py
magicrf/case2.py
magicrf-1.2.dist-info/LICENSE
magicrf-1.2.dist-info/METADATA
magicrf-1.2.dist-info/WHEEL
magicrf-1.2.dist-info/top_level.txt
magicrf-1.2.dist-info/RECORD
