Metadata-Version: 2.1
Name: magicrf
Version: 1.2
Summary: Library for UHF RFID Soc Reader Chip M100 and QM100
Home-page: https://github.com/hex-in/libmagicrf.git
Author: Heyn
Author-email: heyunhuan@gmail.com
License: MIT
Keywords: UHF,M100,QM100,rfid,magicrf
Platform: any
Classifier: Development Status :: 3 - Alpha
Classifier: Intended Audience :: Developers
Classifier: Topic :: Software Development :: Build Tools
Classifier: License :: OSI Approved :: MIT License
Classifier: Programming Language :: Python :: 3
Classifier: Programming Language :: Python :: 3.6
Classifier: Programming Language :: Python :: Implementation :: CPython
Classifier: Programming Language :: Python :: Implementation :: PyPy
Requires-Dist: pyserial (>=3.4)
